scraping.py
suzo.py
text.py
utils.py
SuZo-1.0.9.dist-info/DESCRIPTION.rst
SuZo-1.0.9.dist-info/METADATA
SuZo-1.0.9.dist-info/RECORD
SuZo-1.0.9.dist-info/WHEEL
SuZo-1.0.9.dist-info/entry_points.txt
SuZo-1.0.9.dist-info/metadata.json
SuZo-1.0.9.dist-info/top_level.txt
