Metadata-Version: 2.0
Name: SuZo
Version: 1.0.9
Summary: Um comparador automático para labs do sistema SuSy
Home-page: https://github.com/muztake/suzo
Author: Henrique Cunha
Author-email: henrycunh@gmail.com
License: UNKNOWN
Keywords: comparador parser susy unicamp
Platform: UNKNOWN
Requires-Python: >=3
Requires-Dist: Colorama
Requires-Dist: PyQuery
Requires-Dist: click
